steganan/__init__.py
steganan/io.py
steganan/steganan.py
steganan-0.2.2.dist-info/METADATA
steganan-0.2.2.dist-info/WHEEL
steganan-0.2.2.dist-info/licenses/LICENSE
steganan-0.2.2.dist-info/RECORD
