Metadata-Version: 2.4
Name: steganan
Version: 0.2.2
Summary: Steganography in floating point data with NaN payloads
Project-URL: Homepage, https://github.com/kjordahl/steganan
Project-URL: Repository, https://github.com/kjordahl/steganan
Author-email: Kelsey Jordahl <kjordahl@alum.mit.edu>
License-File: LICENSE
Keywords: python
Classifier: Development Status :: 3 - Alpha
Classifier: Intended Audience :: Developers
Classifier: License :: OSI Approved :: MIT License
Classifier: Programming Language :: Python
Classifier: Programming Language :: Python :: 3
Classifier: Programming Language :: Python :: 3.9
Classifier: Programming Language :: Python :: 3.10
Classifier: Programming Language :: Python :: 3.11
Classifier: Programming Language :: Python :: 3.12
Classifier: Programming Language :: Python :: 3.13
Classifier: Topic :: Software Development :: Libraries :: Python Modules
Requires-Python: >=3.9
Requires-Dist: imageio>=2.37.0
Requires-Dist: numpy>=2.0.2
Requires-Dist: tifffile>=2024.8.30
